sslog/__init__.py
sslog/_base.py
sslog/_catch.py
sslog/_default.py
sslog/_out.py
sslog/_process.py
sslog/py.typed
sslog-0.0.0a52.dist-info/WHEEL
sslog-0.0.0a52.dist-info/METADATA
sslog-0.0.0a52.dist-info/RECORD
